{
  "id": "1913656",
  "name": "账本",
  "font_family": "iconfont",
  "css_prefix_text": "icon-",
  "description": "",
  "glyphs": [
    {
      "icon_id": "970718",
      "name": "plus",
      "font_class": "plus",
      "unicode": "e610",
      "unicode_decimal": 58896
    },
    {
      "icon_id": "11231648",
      "name": "plus",
      "font_class": "plus1",
      "unicode": "e786",
      "unicode_decimal": 59270
    },
    {
      "icon_id": "151695",
      "name": "down",
      "font_class": "down",
      "unicode": "e662",
      "unicode_decimal": 58978
    },
    {
      "icon_id": "1393637",
      "name": "down",
      "font_class": "down1",
      "unicode": "e6e9",
      "unicode_decimal": 59113
    },
    {
      "icon_id": "100585",
      "name": "记账本",
      "font_class": "jizhang",
      "unicode": "e60f",
      "unicode_decimal": 58895
    },
    {
      "icon_id": "887965",
      "name": "我的 (2)",
      "font_class": "wode2",
      "unicode": "e631",
      "unicode_decimal": 58929
    },
    {
      "icon_id": "3315400",
      "name": "我的",
      "font_class": "wode",
      "unicode": "e625",
      "unicode_decimal": 58917
    },
    {
      "icon_id": "6997483",
      "name": "我 的",
      "font_class": "wodedangxuan",
      "unicode": "e607",
      "unicode_decimal": 58887
    },
    {
      "icon_id": "8471207",
      "name": "记账",
      "font_class": "jizhang1",
      "unicode": "e6bd",
      "unicode_decimal": 59069
    },
    {
      "icon_id": "8987348",
      "name": "明细",
      "font_class": "mingxi",
      "unicode": "e68a",
      "unicode_decimal": 59018
    },
    {
      "icon_id": "14163799",
      "name": "记账本",
      "font_class": "jizhangben",
      "unicode": "e64d",
      "unicode_decimal": 58957
    },
    {
      "icon_id": "14465067",
      "name": "delete",
      "font_class": "delete",
      "unicode": "e669",
      "unicode_decimal": 58985
    },
    {
      "icon_id": "386219",
      "name": "备注",
      "font_class": "beizhu",
      "unicode": "e60a",
      "unicode_decimal": 58890
    },
    {
      "icon_id": "674979",
      "name": "日历",
      "font_class": "calendar",
      "unicode": "e679",
      "unicode_decimal": 59001
    },
    {
      "icon_id": "10715428",
      "name": "日历",
      "font_class": "rili",
      "unicode": "e634",
      "unicode_decimal": 58932
    },
    {
      "icon_id": "5135",
      "name": "数码手机",
      "font_class": "shumashouji",
      "unicode": "e600",
      "unicode_decimal": 58880
    },
    {
      "icon_id": "82381",
      "name": "游戏",
      "font_class": "94",
      "unicode": "e67e",
      "unicode_decimal": 59006
    },
    {
      "icon_id": "101277",
      "name": "住房",
      "font_class": "zhufang",
      "unicode": "e653",
      "unicode_decimal": 58963
    },
    {
      "icon_id": "1048451",
      "name": "日用品",
      "font_class": "riyongpin",
      "unicode": "e63f",
      "unicode_decimal": 58943
    },
    {
      "icon_id": "1079503",
      "name": "数码",
      "font_class": "shuma",
      "unicode": "e630",
      "unicode_decimal": 58928
    },
    {
      "icon_id": "1160975",
      "name": "steam",
      "font_class": "steam",
      "unicode": "e8df",
      "unicode_decimal": 59615
    },
    {
      "icon_id": "1315580",
      "name": "超市",
      "font_class": "chaoshi",
      "unicode": "e602",
      "unicode_decimal": 58882
    },
    {
      "icon_id": "1346666",
      "name": "淘宝",
      "font_class": "taobao",
      "unicode": "e633",
      "unicode_decimal": 58931
    },
    {
      "icon_id": "1486838",
      "name": "水果",
      "font_class": "shuiguo",
      "unicode": "e62f",
      "unicode_decimal": 58927
    },
    {
      "icon_id": "2767701",
      "name": "餐饮",
      "font_class": "icon-",
      "unicode": "e645",
      "unicode_decimal": 58949
    },
    {
      "icon_id": "5238520",
      "name": "银行卡",
      "font_class": "shuaqiaqiapianyinhangqia",
      "unicode": "e622",
      "unicode_decimal": 58914
    },
    {
      "icon_id": "6400262",
      "name": "缴费",
      "font_class": "weibiaoti--",
      "unicode": "e613",
      "unicode_decimal": 58899
    },
    {
      "icon_id": "7302534",
      "name": "支付宝 账户",
      "font_class": "zhifubaozhanghu",
      "unicode": "e60b",
      "unicode_decimal": 58891
    },
    {
      "icon_id": "7790995",
      "name": "工资",
      "font_class": "gongzi",
      "unicode": "e7e9",
      "unicode_decimal": 59369
    },
    {
      "icon_id": "10262050",
      "name": "设 置",
      "font_class": "shezhi",
      "unicode": "e611",
      "unicode_decimal": 58897
    },
    {
      "icon_id": "11749436",
      "name": "医疗",
      "font_class": "yiliao",
      "unicode": "e682",
      "unicode_decimal": 59010
    },
    {
      "icon_id": "12796369",
      "name": "医疗",
      "font_class": "yiliao1",
      "unicode": "e636",
      "unicode_decimal": 58934
    },
    {
      "icon_id": "15378665",
      "name": "origin",
      "font_class": "origin",
      "unicode": "ec49",
      "unicode_decimal": 60489
    }
  ]
}
